MANIFEST.in
README.md
VERSION
requirements.txt
setup.py
docs/source/conf.py
examples/create_jws.py
examples/default_secret_key.py
examples/simple-azure-sign.py
examples/simple-azure.py
examples/simple-disk.py
examples/simple-google-sign.py
examples/trust-jwks.py
examples/trust-oauth.py
unimatrix.ext.crypto.egg-info/PKG-INFO
unimatrix.ext.crypto.egg-info/SOURCES.txt
unimatrix.ext.crypto.egg-info/dependency_links.txt
unimatrix.ext.crypto.egg-info/entry_points.txt
unimatrix.ext.crypto.egg-info/requires.txt
unimatrix.ext.crypto.egg-info/top_level.txt
unimatrix/ext/crypto/__boot__.py
unimatrix/ext/crypto/__init__.py
unimatrix/ext/crypto/abstractkeystore.py
unimatrix/ext/crypto/apps.py
unimatrix/ext/crypto/ciphertext.py
unimatrix/ext/crypto/conf.py
unimatrix/ext/crypto/const.py
unimatrix/ext/crypto/decrypter.py
unimatrix/ext/crypto/defaultkeystore.py
unimatrix/ext/crypto/depends.py
unimatrix/ext/crypto/encrypter.py
unimatrix/ext/crypto/exceptions.py
unimatrix/ext/crypto/ioc.py
unimatrix/ext/crypto/jwk.py
unimatrix/ext/crypto/keychain.py
unimatrix/ext/crypto/keyloader.py
unimatrix/ext/crypto/oid.py
unimatrix/ext/crypto/package.json
unimatrix/ext/crypto/parsing.py
unimatrix/ext/crypto/pem.py
unimatrix/ext/crypto/plaintext.py
unimatrix/ext/crypto/policy.py
unimatrix/ext/crypto/private.py
unimatrix/ext/crypto/public.py
unimatrix/ext/crypto/secret.py
unimatrix/ext/crypto/settings.py
unimatrix/ext/crypto/signable.py
unimatrix/ext/crypto/signature.py
unimatrix/ext/crypto/signer.py
unimatrix/ext/crypto/symmetric.py
unimatrix/ext/crypto/trustedpublickey.py
unimatrix/ext/crypto/truststore.py
unimatrix/ext/crypto/urls.py
unimatrix/ext/crypto/utils.py
unimatrix/ext/crypto/verifier.py
unimatrix/ext/crypto/algorithms/__init__.py
unimatrix/ext/crypto/algorithms/aes.py
unimatrix/ext/crypto/algorithms/base.py
unimatrix/ext/crypto/algorithms/ec.py
unimatrix/ext/crypto/algorithms/encryption.py
unimatrix/ext/crypto/algorithms/hmac.py
unimatrix/ext/crypto/algorithms/rsa.py
unimatrix/ext/crypto/algorithms/signing.py
unimatrix/ext/crypto/backends/__init__.py
unimatrix/ext/crypto/backends/azure.py
unimatrix/ext/crypto/backends/disk.py
unimatrix/ext/crypto/backends/google/__init__.py
unimatrix/ext/crypto/ec/__init__.py
unimatrix/ext/crypto/ec/private.py
